{
	"blogs": [
		{"id": 1, "title": "인플루언서 이가흔", "tag": "Lifestyle", "src": "../img/jestina/blog-1.jpg", "content": "#제이에스티나 #제이에스티나가방 #파이백 #크로스백 @lee_gaheun #이가흔"},
		{"id": 2, "title": "인플루언서 정송이", "tag": "Lifestyle", "src": "../img//jestina/blog-2.jpg", "content": "#제이에스티나 #제이에스티나가방 #조엘이지새들백 #새들백 #크로스백 #숄더백 @__yyyj #정송이"},
		{"id": 3, "title": "인플루언서 한슬", "tag": "Lifestyle", "src": "../img/jestina/blog-3.jpg", "content": "#제이에스티나 #제이에스티나가방 #사라백 #토드백 #숄더백 #@life_seul #한슬"},
		{"id": 4, "title": "인플루언서 주연정", "tag": "Lifestyle", "src": "../img/jestina/blog-4.jpg", "content": "#제이에스티나 #제이에스티나가방 #조엘퀼팅백 #호보백 #여름아이템 #@y__eonj #주연정"},
		{"id": 5, "title": "인플루언서 이채은", "tag": "Lifestyle", "src": "../img/jestina/blog-5.jpg", "content": "#제이에스티나 #제이에스티나가방 #사라토트백 #크로스백 #여름아이템 #@c_eeeun #이채은"}
	]
}